guillotina_batch/__init__.py
guillotina_batch/api.py
guillotina_batch/py.typed
guillotina_batch/tests/__init__.py
guillotina_batch/tests/conftest.py
guillotina_batch/tests/fixtures.py
guillotina_batch/tests/package.py
guillotina_batch/tests/test_batch.py
guillotina_batch/tests/test_batch_eager_commit.py
guillotina_batch-6.0.0.dist-info/METADATA
guillotina_batch-6.0.0.dist-info/WHEEL
guillotina_batch-6.0.0.dist-info/top_level.txt
guillotina_batch-6.0.0.dist-info/RECORD
