Metadata-Version: 2.1
Name: guillotina-batch
Version: 6.0.0
Summary: batch endpoint for guillotina
Home-page: https://github.com/guillotinaweb/guillotina_batch
Author: Nathan Van Gheem
Author-email: vangheem@gmail.com
License: BSD
Platform: UNKNOWN
Classifier: License :: OSI Approved :: BSD License
Classifier: Programming Language :: Python :: 3.7
Classifier: Programming Language :: Python :: 3.8
Classifier: Topic :: Software Development :: Libraries :: Python Modules
Classifier: Topic :: Internet :: WWW/HTTP
Classifier: Intended Audience :: Developers
Requires-Dist: guillotina (>=6.0.0b5)
Requires-Dist: backoff
Provides-Extra: test
Requires-Dist: pytest (>=4.1.1) ; extra == 'test'
Requires-Dist: aiohttp (<4.0.0,>=3.6.0) ; extra == 'test'
Requires-Dist: docker ; extra == 'test'
Requires-Dist: backoff ; extra == 'test'
Requires-Dist: jsonschema (==2.6.0) ; extra == 'test'
Requires-Dist: psycopg2-binary ; extra == 'test'
Requires-Dist: pytest-asyncio (==0.10.0) ; extra == 'test'
Requires-Dist: pytest-cov ; extra == 'test'
Requires-Dist: coverage (==4.4.0) ; extra == 'test'
Requires-Dist: pytest-docker-fixtures ; extra == 'test'
Requires-Dist: asyncpg (==0.15.0) ; extra == 'test'
Requires-Dist: async-asgi-testclient (==1.4.4) ; extra == 'test'
